medicalimageanalysis/__init__.py
medicalimageanalysis/data.py
medicalimageanalysis/reader.py
medicalimageanalysis/read/__init__.py
medicalimageanalysis/read/dicom.py
medicalimageanalysis/read/mf3.py
medicalimageanalysis/read/mhd.py
medicalimageanalysis/read/stl.py
medicalimageanalysis/read/vtk.py
medicalimageanalysis/structure/__init__.py
medicalimageanalysis/structure/deformable.py
medicalimageanalysis/structure/dose.py
medicalimageanalysis/structure/image.py
medicalimageanalysis/structure/poi.py
medicalimageanalysis/structure/rigid.py
medicalimageanalysis/structure/roi.py
medicalimageanalysis/utils/__init__.py
medicalimageanalysis/utils/conversion.py
medicalimageanalysis/utils/creation.py
medicalimageanalysis/utils/convert/__init__.py
medicalimageanalysis/utils/convert/contour.py
medicalimageanalysis/utils/deformable/__init__.py
medicalimageanalysis/utils/deformable/simpleitk.py
medicalimageanalysis/utils/image/__init__.py
medicalimageanalysis/utils/image/threshold.py
medicalimageanalysis/utils/image/transform.py
medicalimageanalysis/utils/mesh/__init__.py
medicalimageanalysis/utils/mesh/surface.py
medicalimageanalysis/utils/mesh/volume.py
medicalimageanalysis/utils/rigid/__init__.py
medicalimageanalysis/utils/rigid/icp.py
medicalimageanalysis/utils/roi/__init__.py
medicalimageanalysis/utils/roi/contour.py
medicalimageanalysis-2.1.87.dist-info/licenses/LICENSE.txt
medicalimageanalysis-2.1.87.dist-info/METADATA
medicalimageanalysis-2.1.87.dist-info/WHEEL
medicalimageanalysis-2.1.87.dist-info/top_level.txt
medicalimageanalysis-2.1.87.dist-info/RECORD
